babylog/__init__.py
babylog/babylog.py
babylog/config.py
babylog/data_utils.py
babylog/deserialize.py
babylog/logger.py
babylog/pubsub.py
babylog/utils.py
babylog/protobuf/__init__.py
babylog/protobuf/babylog_stream_pb2.py
babylog/protobuf/babylog_stream_pb2.pyi
babylog-1.0.2.dist-info/METADATA
babylog-1.0.2.dist-info/WHEEL
babylog-1.0.2.dist-info/RECORD
