Metadata-Version: 2.1
Name: babylog
Version: 1.0.2
Summary: A lightweight library for logging image and prediction data for your ML and computer vision models in production.
Project-URL: Homepage, https://github.com/thebabylonai/babylog
Project-URL: Bug Tracker, https://github.com/thebabylonai/babylog/issues
Author-email: "BabylonAI, Inc." <support@babylonai.dev>, Ahmad Roumie <ahmad@babylonai.dev>, Rangel Milushev <rangel@babylonai.dev>
Classifier: Development Status :: 4 - Beta
Classifier: License :: OSI Approved :: Apache Software License
Classifier: Operating System :: OS Independent
Classifier: Programming Language :: Python :: 3
Requires-Python: >=3.8
Requires-Dist: boto3==1.15.3
Requires-Dist: numpy==1.24.1
Requires-Dist: opencv-python==4.7.0.68
Requires-Dist: protobuf==4.21.12
Requires-Dist: pyyaml==6.0
Requires-Dist: zmq==0.0.0
